[
  {
    "headline": "Get Started",
    "items": [
      { "id": 1, "label": "Introduction", "link": "/docs/introduction" },
      { "id": 2, "label": "Installation", "link": "/docs/installation" }
    ]
  },
  {
    "headline": "Components",
    "items": [
      {
        "id": 1,
        "label": "Month Slider",
        "link": "/docs/components/month-slider",
        "isNew": true
      },
      {
        "id": 2,
        "label": "Rotate Cards",
        "link": "/docs/components/rotate-cards",
        "isNew": true
      },
      {
        "id": 2,
        "label": "Swiper",
        "link": "/docs/components/swiper",
        "comingSoon": true
      }
    ]
  }
]
